script/__init__.py
script/start.py
script/tasks/__init__.py
script/tasks/launch.py
script/tasks/open_project.py
script/ui_tools/UI_tools.py
script/ui_tools/__init__.py
script/utils/__init__.py
script/utils/utils.py
nowyou_grafits_script_python-1.1.3.dist-info/METADATA
nowyou_grafits_script_python-1.1.3.dist-info/WHEEL
nowyou_grafits_script_python-1.1.3.dist-info/top_level.txt
nowyou_grafits_script_python-1.1.3.dist-info/RECORD
