Metadata-Version: 2.1
Name: nowyou-grafits-script-python
Version: 1.1.3
Summary: Now you project grafis scripts
Home-page: https://bitbucket.org/inventilabs/nowyou-grafis-script-python/
Author: Alex Mensak
Author-email: alexander.mensak@ilabs.cz
License: UNKNOWN
Keywords: nowyou python
Platform: UNKNOWN
Classifier: Development Status :: 3 - Alpha
Classifier: Intended Audience :: Developers
Classifier: Topic :: Software Development :: Libraries
Classifier: License :: Other/Proprietary License
Classifier: Programming Language :: Python :: 3
Requires-Python: >=3.6
